PITpip/PITpip.py
PITpip/__init__.py
pitpip-1.4.1.dist-info/METADATA
pitpip-1.4.1.dist-info/WHEEL
pitpip-1.4.1.dist-info/licenses/LICENSE
pitpip-1.4.1.dist-info/RECORD
