Metadata-Version: 2.3
Name: PITpip
Version: 1.4.1
Summary: A small test package for testing package versioning
Project-URL: Homepage, https://github.com/JPHaapaniemi/package-import-test-pip
Author-email: Jukka-Pekka Haapaniemi <jp.haapaniemi@riverit.fi>
License-File: LICENSE
Classifier: License :: OSI Approved :: Apache Software License
Classifier: Operating System :: OS Independent
Classifier: Programming Language :: Python :: 3
Requires-Python: >=3.8
